LICENSE
README.txt
setup.cfg
setup.py
CROC.egg-info/PKG-INFO
CROC.egg-info/SOURCES.txt
CROC.egg-info/dependency_links.txt
CROC.egg-info/requires.txt
CROC.egg-info/top_level.txt
croc/__init__.py
croc/_static_version.py
croc/_version.py
croc/area.py
croc/average.py
croc/bedroc.py
croc/curve.py
scripts/croc-area
scripts/croc-average
scripts/croc-bedroc
scripts/croc-curve